llama_index/readers/zyte_serp/__init__.py
llama_index/readers/zyte_serp/base.py
llama_index_readers_zyte_serp-0.3.1.dist-info/METADATA
llama_index_readers_zyte_serp-0.3.1.dist-info/WHEEL
llama_index_readers_zyte_serp-0.3.1.dist-info/licenses/LICENSE
llama_index_readers_zyte_serp-0.3.1.dist-info/RECORD
